LICENSE
MANIFEST.in
README.rst
setup.cfg
setup.py
django_rest_mock.egg-info/PKG-INFO
django_rest_mock.egg-info/SOURCES.txt
django_rest_mock.egg-info/dependency_links.txt
django_rest_mock.egg-info/not-zip-safe
django_rest_mock.egg-info/requires.txt
django_rest_mock.egg-info/top_level.txt
rest_mock_server/__init__.py
rest_mock_server/__version__.py
rest_mock_server/apps.py
rest_mock_server/builder.py
rest_mock_server/models.py
rest_mock_server/core/__init__.py
rest_mock_server/core/express.py
rest_mock_server/core/extractor.py
rest_mock_server/core/factory.py
rest_mock_server/core/functions.py
rest_mock_server/core/parser.py
rest_mock_server/core/structures.py
rest_mock_server/core/utils.py
rest_mock_server/core/js/datafinder.js
rest_mock_server/core/js/gethandler.js
rest_mock_server/core/js/modifyhandler.js
rest_mock_server/core/js/posthandler.js
rest_mock_server/core/templates/endpoint.template
rest_mock_server/core/templates/express.template
rest_mock_server/core/templates/response.template
rest_mock_server/core/templates/variable.template
rest_mock_server/management/__init__.py
rest_mock_server/management/__pycache__/__init__.cpython-36.pyc
rest_mock_server/management/commands/__init__.py
rest_mock_server/management/commands/genmockserver.py
rest_mock_server/management/commands/startmockserver.py
rest_mock_server/management/commands/__pycache__/__init__.cpython-36.pyc
rest_mock_server/management/commands/__pycache__/genmockserver.cpython-36.pyc
rest_mock_server/management/commands/__pycache__/startmockserver.cpython-36.pyc