Metadata-Version: 1.1
Name: django-rest-mock
Version: 0.2.9
Summary: Mock Express server generated based on your views, that can come in handy when developing REST APIs with Django
Home-page: https://github.com/thomasjiangcy/django-rest-mock-server
Author: Thomas Jiang
Author-email: thomasjiangcy@gmail.com
License: MIT
Platform: UNKNOWN
Classifier: Framework :: Django
Classifier: Framework :: Django :: 1.11
Classifier: Framework :: Django :: 2.0
Classifier: Programming Language :: Python :: 3
Classifier: Programming Language :: Python :: 3.4
Classifier: Programming Language :: Python :: 3.5
Classifier: Programming Language :: Python :: 3.6
Classifier: Topic :: Software Development :: Libraries :: Python Modules
